any2cos/__init__.py
any2cos/api.py
any2cos/cli.py
any2cos/remote_pyplot.py
any2cos/utils/__init__.py
any2cos/utils/ali_func_utils.py
any2cos/utils/cfg_manner.py
any2cos-0.1.6.dist-info/METADATA
any2cos-0.1.6.dist-info/WHEEL
any2cos-0.1.6.dist-info/entry_points.txt
any2cos-0.1.6.dist-info/top_level.txt
any2cos-0.1.6.dist-info/RECORD
