Metadata-Version: 2.4
Name: any2cos
Version: 0.1.6
Requires-Python: >=3.7
Requires-Dist: alibabacloud_oss_v2
Requires-Dist: rich
Requires-Dist: matplotlib
Dynamic: requires-dist
Dynamic: requires-python
